README.rst
setup.cfg
setup.py
papago/__init__.py
papago/compat.py
papago/contants.py
papago/response.py
papago/translator.py
papago.egg-info/PKG-INFO
papago.egg-info/SOURCES.txt
papago.egg-info/dependency_links.txt
papago.egg-info/not-zip-safe
papago.egg-info/top_level.txt
tests/__init__.py
tests/compat.py
tests/test_response.py
tests/test_translator.py