Metadata-Version: 1.1
Name: papago
Version: 1.0.0
Summary: PAPAGO translate API with Python
Home-page: https://github.com/stunstunstun/papago
Author: stunstunstun
Author-email: agileboys.com@gmail.com
License: MIT
Platform: UNKNOWN
Classifier: Programming Language :: Python :: 2.7
Classifier: Programming Language :: Python :: 3
Classifier: Programming Language :: Python :: 3.6
